AUTHORS.md
CONTRIBUTING.md
HISTORY.md
LICENSE
MANIFEST.in
README.md
setup.cfg
setup.py
django_better_admin_arrayfield/__init__.py
django_better_admin_arrayfield/apps.py
django_better_admin_arrayfield/admin/mixins.py
django_better_admin_arrayfield/forms/__init__.py
django_better_admin_arrayfield/forms/fields.py
django_better_admin_arrayfield/forms/widgets.py
django_better_admin_arrayfield/models/__init__.py
django_better_admin_arrayfield/models/fields.py
django_better_admin_arrayfield/static/css/django_better_admin_arrayfield.css
django_better_admin_arrayfield/static/css/min/django_better_admin_arrayfield.min.css
django_better_admin_arrayfield/static/js/django_better_admin_arrayfield.js
django_better_admin_arrayfield/static/js/min/django_better_admin_arrayfield.min.js
django_better_admin_arrayfield/templates/django_better_admin_arrayfield/forms/widgets/dynamic_array.html
maykin_django_better_admin_arrayfield.egg-info/PKG-INFO
maykin_django_better_admin_arrayfield.egg-info/SOURCES.txt
maykin_django_better_admin_arrayfield.egg-info/dependency_links.txt
maykin_django_better_admin_arrayfield.egg-info/not-zip-safe
maykin_django_better_admin_arrayfield.egg-info/top_level.txt