Metadata-Version: 2.1
Name: maykin-django-better-admin-arrayfield
Version: 1.0.5
Summary: Better ArrayField widget for admin
Home-page: https://github.com/maykinmedia/django-better-admin-arrayfield
Author: Jakub Semik, Maykin Media
Author-email: info@maykinmedia.nl
License: MIT
Keywords: django-better-admin-arrayfield
Platform: UNKNOWN
Classifier: Development Status :: 5 - Production/Stable
Classifier: Framework :: Django :: 2.0
Classifier: Framework :: Django :: 2.1
Classifier: Framework :: Django :: 2.2
Classifier: Intended Audience :: Developers
Classifier: License :: OSI Approved :: MIT License
Classifier: Natural Language :: English
Classifier: Programming Language :: Python :: 3
Classifier: Programming Language :: Python :: 3.5
Classifier: Programming Language :: Python :: 3.6
Classifier: Programming Language :: Python :: 3.7
